CHANGES.rst
LICENSE
MANIFEST.in
Makefile
README.rst
lgpl-2.1.txt
pylintrc
run_unit_tests.py
setup.cfg
setup.py
testing.html
bitnomon/__init__.py
bitnomon/__main__.py
bitnomon/about.py
bitnomon/age.py
bitnomon/bitcoinconf.py
bitnomon/bitnomon_rc.py
bitnomon/formatting.py
bitnomon/main.py
bitnomon/perfprobe.py
bitnomon/qbitcoinrpc.py
bitnomon/qsettings.py
bitnomon/qtwrapper.py
bitnomon/rrdmodel.py
bitnomon/ui_about.py
bitnomon/ui_main.py
bitnomon.egg-info/PKG-INFO
bitnomon.egg-info/SOURCES.txt
bitnomon.egg-info/dependency_links.txt
bitnomon.egg-info/entry_points.txt
bitnomon.egg-info/requires.txt
bitnomon.egg-info/top_level.txt
bitnomon/res/about.ui
bitnomon/res/bitnomon.qrc
bitnomon/res/main.ui
bitnomon/res/128x128/bitnomon.png
bitnomon/res/16x16/bitnomon.png
bitnomon/res/256x256/bitnomon.png
bitnomon/res/32x32/bitnomon.png
bitnomon/res/48x48/bitnomon.png
bitnomon/res/512x512/bitnomon.png
bitnomon/res/64x64/bitnomon.png
bitnomon/res/scalable/bitnomon.svg
deps/install_freedesktop-0.1.2.tar.gz
deps/pyqtgraph/pyqtgraph/PlotData.py
deps/pyqtgraph/pyqtgraph/Point.py
deps/pyqtgraph/pyqtgraph/Qt.py
deps/pyqtgraph/pyqtgraph/SRTTransform.py
deps/pyqtgraph/pyqtgraph/SRTTransform3D.py
deps/pyqtgraph/pyqtgraph/SignalProxy.py
deps/pyqtgraph/pyqtgraph/ThreadsafeTimer.py
deps/pyqtgraph/pyqtgraph/Transform3D.py
deps/pyqtgraph/pyqtgraph/Vector.py
deps/pyqtgraph/pyqtgraph/WidgetGroup.py
deps/pyqtgraph/pyqtgraph/__init__.py
deps/pyqtgraph/pyqtgraph/colormap.py
deps/pyqtgraph/pyqtgraph/configfile.py
deps/pyqtgraph/pyqtgraph/debug.py
deps/pyqtgraph/pyqtgraph/exceptionHandling.py
deps/pyqtgraph/pyqtgraph/frozenSupport.py
deps/pyqtgraph/pyqtgraph/functions.py
deps/pyqtgraph/pyqtgraph/graphicsWindows.py
deps/pyqtgraph/pyqtgraph/numpy_fix.py
deps/pyqtgraph/pyqtgraph/ordereddict.py
deps/pyqtgraph/pyqtgraph/pgcollections.py
deps/pyqtgraph/pyqtgraph/ptime.py
deps/pyqtgraph/pyqtgraph/python2_3.py
deps/pyqtgraph/pyqtgraph/reload.py
deps/pyqtgraph/pyqtgraph/units.py
deps/pyqtgraph/pyqtgraph/GraphicsScene/GraphicsScene.py
deps/pyqtgraph/pyqtgraph/GraphicsScene/__init__.py
deps/pyqtgraph/pyqtgraph/GraphicsScene/exportDialog.py
