Metadata-Version: 1.1
Name: bitnomon
Version: 0.1.1
Summary: Monitoring/visualization GUI for a Bitcoin node
Home-page: https://www.welshcomputing.com/code/bitnomon.html
Author: Jacob Welsh
Author-email: jacob@welshcomputing.com
License: Apache License 2.0
Keywords: bitcoin blockchain monitoring visualization pyqtgraph rrdtool
Platform: UNKNOWN
Classifier: Development Status :: 3 - Alpha
Classifier: Environment :: MacOS X
Classifier: Environment :: Win32 (MS Windows)
Classifier: Environment :: X11 Applications :: Qt
Classifier: Intended Audience :: End Users/Desktop
Classifier: Intended Audience :: System Administrators
Classifier: License :: OSI Approved :: Apache Software License
Classifier: Natural Language :: English
Classifier: Operating System :: POSIX
Classifier: Operating System :: MacOS :: MacOS X
Classifier: Operating System :: Microsoft :: Windows
Classifier: Programming Language :: Python
Classifier: Programming Language :: Python :: 2.7
Classifier: Programming Language :: Python :: 3
Classifier: Topic :: Scientific/Engineering :: Visualization
Classifier: Topic :: System :: Monitoring
